mcp_deploy/__init__.py
mcp_deploy/__main__.py
mcp_deploy/mcp_handlers.py
mcp_deploy/models.py
mcp_deploy/server.py
mcp_deploy-0.1.12.dist-info/METADATA
mcp_deploy-0.1.12.dist-info/WHEEL
mcp_deploy-0.1.12.dist-info/entry_points.txt
mcp_deploy-0.1.12.dist-info/RECORD
