Metadata-Version: 2.4
Name: mcp-deploy
Version: 0.1.12
Summary: MCP Deploy Server
Author-email: David <guowei1461@gmail.com>
Keywords: deploy,mcp
Requires-Python: >=3.12
Requires-Dist: fastapi
Requires-Dist: httpx
Requires-Dist: mcp
Requires-Dist: pydantic
Requires-Dist: requests
Requires-Dist: uvicorn
